cyclotron_std/__init__.py
cyclotron_std/argparse.py
cyclotron_std/logging.py
cyclotron_std/io/__init__.py
cyclotron_std/io/file.py
cyclotron_std/os/__init__.py
cyclotron_std/os/walk.py
cyclotron_std/sys/__init__.py
cyclotron_std/sys/argv.py
cyclotron_std/sys/stdout.py
cyclotron_std-2.0.0.dist-info/LICENSE.txt
cyclotron_std-2.0.0.dist-info/METADATA
cyclotron_std-2.0.0.dist-info/WHEEL
cyclotron_std-2.0.0.dist-info/top_level.txt
cyclotron_std-2.0.0.dist-info/RECORD
