Metadata-Version: 2.1
Name: cyclotron-std
Version: 2.0.0
Summary: Standard library drivers and components for cyclotron
Author: Romain Picard
Author-email: romain.picard@oakbits.com
License: Copyright (c) 2018 by Romain Picard
Project-URL: repository, https://github.com/MainRo/cyclotron-std.git
Keywords: reactivex,cyclotron,cyclejs
Classifier: Development Status :: 5 - Production/Stable
Classifier: Intended Audience :: Developers
Classifier: Programming Language :: Python :: 3
Requires-Python: >=3.7
License-File: LICENSE.txt
Requires-Dist: reactivex (~=4.0)
Requires-Dist: cyclotron (~=2.0)
Provides-Extra: test
Requires-Dist: pytest ; extra == 'test'
